convertanything/__init__.py
convertanything-0.0.16.dist-info/LICENSE
convertanything-0.0.16.dist-info/METADATA
convertanything-0.0.16.dist-info/WHEEL
convertanything-0.0.16.dist-info/top_level.txt
convertanything-0.0.16.dist-info/RECORD
