Metadata-Version: 2.1
Name: convertanything
Version: 0.0.16
Summary: convertanything is a Python package that allows you to convert any text into a structured format according to the schema provided.
Author: Josh XT
Author-email: josh@devxt.com
Requires-Python: >=3.10
License-File: LICENSE
Requires-Dist: pydantic
Requires-Dist: openai
